{
  "question_id": "question-038",
  "title": "Scatterplot",
  "difficulty": "Easy",
  "question_text": "<div class=\"paragraph\">Which of the following is <em>not</em> usually included when describing a scatterplot?</div>",
  "image_files": [],
  "choices": [
    {
      "letter": "A",
      "text": "Form"
    },
    {
      "letter": "B",
      "text": "Symmetry"
    },
    {
      "letter": "C",
      "text": "Direction"
    },
    {
      "letter": "D",
      "text": "Unusual Features"
    },
    {
      "letter": "E",
      "text": "Strength"
    }
  ],
  "correct_answer": "<strong>Choice 'B'</strong> is the correct answer.",
  "solution": "",
  "distractor_explanations": {},
  "tags": [
    "DAT-1.A.1",
    "DAT-1",
    "DAT-1.A",
    "2.A"
  ],
  "standards": [
    "DAT-1.A.1",
    "DAT-1",
    "DAT-1.A",
    "2.A"
  ]
}