{
  "question_id": "question-001",
  "unit": "Unit 2 | Exploring Two-Variable Data",
  "title": "Quantitative Relationship for Cars",
  "difficulty": "Easy",
  "question_text": "Which option below does NOT describe a relationship between two quantitative variables for cars?",
  "image_files": [],
  "choices": [
    {
      "letter": "A",
      "text": "The size of a gas tank of a car and the number of miles it can be driven on a tank of gas."
    },
    {
      "letter": "B",
      "text": "The miles per gallon a car gets and the number of miles it can be driven on a tank of gas."
    },
    {
      "letter": "C",
      "text": "The miles per gallon a car gets and the type of car that it is."
    },
    {
      "letter": "D",
      "text": "The size of the gas tank of a car and the number of times the tank is filled per month."
    },
    {
      "letter": "E",
      "text": "The number of times a gas tank is filled per month and the miles driven by the car."
    }
  ],
  "correct_answer": "Choice 'C' is the correct answer.",
  "solution": "",
  "distractor_explanations": {},
  "tags": [
    "VAR-1.D",
    "VAR-1.D.1",
    "1.A",
    "VAR-1"
  ],
  "standards": [
    "VAR-1.D",
    "VAR-1.D.1",
    "1.A",
    "VAR-1"
  ]
}