{
  "question_id": "question-029",
  "title": "Changes in $t$-distribution with Decrease of D.O.F.",
  "difficulty": "Difficult",
  "question_text": "<div class=\"paragraph\">Which of the following correctly describes the changes in the <span class=\"tex2jax_process\">$t$</span>-distribution when the degrees of freedom decreases?</div>",
  "image_files": [],
  "choices": [
    {
      "letter": "A",
      "text": "The center decreases, the spread increases and the shape becomes less normal."
    },
    {
      "letter": "B",
      "text": "The center decreases, the spread increases and the shape becomes more normal."
    },
    {
      "letter": "C",
      "text": "The center increases, the spread decreases and the shape becomes less normal."
    },
    {
      "letter": "D",
      "text": "The center remains the same, the spread decreases and the shape becomes more normal."
    },
    {
      "letter": "E",
      "text": "The center remains the same, the spread increases and the shape becomes less normal."
    }
  ],
  "correct_answer": "<strong>Choice 'E'</strong> is the correct answer.  ",
  "solution": "",
  "distractor_explanations": {},
  "tags": [
    "VAR-7",
    "VAR-7.A",
    "3.C",
    "VAR-7.A.2"
  ],
  "standards": [
    "VAR-7",
    "VAR-7.A",
    "3.C",
    "VAR-7.A.2"
  ]
}