{
  "question_id": "question-021",
  "unit": "Unit 6 | Inference for Categorical Data: Proportions",
  "title": "Margin of Error Calculation",
  "difficulty": "Difficult",
  "question_text": "A biologist hopes to estimate the proportion of alligators in Florida that are adult. When sampling alligators, the biologist computes the one-proportion $Z$ -interval going from $0.67$ to $0.74$ at $99\\%$ confidence. The margin of error for a $95\\%$ confidence interval would be",
  "image_files": [],
  "choices": [
    {
      "letter": "A",
      "text": "3.5 % 3.5 %"
    },
    {
      "letter": "B",
      "text": "2.66 % 2.66 %"
    },
    {
      "letter": "C",
      "text": "2.58 % 2.58 %"
    },
    {
      "letter": "D",
      "text": "4.25 % 4.25 %"
    },
    {
      "letter": "E",
      "text": "1.96 % 1.96 %"
    }
  ],
  "correct_answer": "Choice 'B' is the correct answer.",
  "solution": "",
  "distractor_explanations": {},
  "tags": [
    "UNC-4.C.4",
    "UNC-4.C.3",
    "3.D",
    "UNC-4.C.2",
    "UNC-4.C.1",
    "UNC-4.C",
    "UNC-4"
  ],
  "standards": [
    "UNC-4.C.4",
    "UNC-4.C.3",
    "3.D",
    "UNC-4.C.2",
    "UNC-4.C.1",
    "UNC-4.C",
    "UNC-4"
  ]
}