{
  "question_id": "question-089",
  "unit": "Unit 6 | Inference for Categorical Data: Proportions",
  "topics": [
    "confidence-interval",
    "estimation",
    "statistical-inference",
    "logic-meaning-properties"
  ],
  "title": "Unemployment Concerns",
  "difficulty": "Hard",
  "question_text": "The threat of unemployment is a major concern for working adults.\nIn a survey of $1{,}500\\text{ working adults}$, $720\\text{ men}$ and $780\\text{ women}$ were asked the question, “Are you concerned about losing your job within the next $12\\text{ months}$?”\nOf those who were surveyed, $312\\text{ males}$ said “yes,” and $240\\text{ females}$ said “yes.”\nWhy would it be considered incorrect to use a one-proportion $Z$-interval in this situation?",
  "image_files": [],
  "tables": [],
  "choices": [
    {
      "letter": "A",
      "text": "This data follows the $T$ distribution."
    },
    {
      "letter": "B",
      "text": "It is not known if the sampling distribution is approximately normal."
    },
    {
      "letter": "C",
      "text": "The data compares two independent proportions."
    },
    {
      "letter": "D",
      "text": "No standard deviation is given."
    },
    {
      "letter": "E",
      "text": "The survey contains apparent bias."
    }
  ],
  "correct_answer": "Choice 'C' is the correct answer.",
  "solution": "",
  "explanations": {},
  "tags": [
    "4.B",
    "UNC-5.D.1",
    "UNC-5",
    "UNC-5.D.2",
    "UNC-5.D"
  ]
}