{
  "question_id": "question-075",
  "title": "Independence: Age and Ownership",
  "difficulty": "Moderate",
  "question_text": "\n<div class=\"markdown-table-wrapper\"><table><thead><tr><th scope=\"col\">Category</th><th scope=\"col\">Own</th><th scope=\"col\">Rent</th></tr></thead><tbody><tr><td>Younger (ages 18-44)</td><td>29</td><td>31</td></tr><tr><td>Older (ages 45 and up)</td><td>27</td><td>13</td></tr></tbody></table></div><br><div class=\"paragraph\"><br>The data chart summarizes the responses of <span class=\"tex2jax_process\"><span class=\"MathJax_Preview\" style=\"color: inherit;\"></span><span id=\"MathJax-Element-9661-Frame\" class=\"mjx-chtml MathJax_CHTML\" tabindex=\"0\" data-mathml=\"<math xmlns=&quot;http://www.w3.org/1998/Math/MathML&quot;><mn>100</mn></math>\" role=\"presentation\" style=\"font-size: 114%; position: relative;\"><span id=\"MJXc-Node-44476\" class=\"mjx-math\" aria-hidden=\"true\"><span id=\"MJXc-Node-44477\" class=\"mjx-mrow\"><span id=\"MJXc-Node-44478\" class=\"mjx-mn\"><span class=\"mjx-char MJXc-TeX-main-R\" style=\"padding-top: 0.387em; padding-bottom: 0.387em;\">100</span></span></span></span><span class=\"MJX_Assistive_MathML\" role=\"presentation\"><math xmlns=\"http://www.w3.org/1998/Math/MathML\"><mn>100</mn></math></span></span><script type=\"math/tex\" id=\"MathJax-Element-9661\">100</script></span> randomly selected individuals in response to the question “Do you own or rent your dwelling?”  </div><div class=\"paragraph\">Does home ownership appear to be independent of age?</div>",
  "image_files": [],
  "choices": [
    {
      "letter": "A",
      "text": "Yes, because the marginal probability of 'Younger' is different from the marginal probability of 'Own.'"
    },
    {
      "letter": "B",
      "text": "Yes, because fewer older people own their homes than younger people do."
    },
    {
      "letter": "C",
      "text": "No, because the conditional probability of 'Younger,' given that a home is owned, is different from the probability of 'Own.'"
    },
    {
      "letter": "D",
      "text": "No, because the probability of 'Own' is different from the conditional probability of 'Own,' given that a person is younger."
    },
    {
      "letter": "E",
      "text": "No, because older people have a more dependable source of income and can afford a home more readily than a younger person can."
    }
  ],
  "correct_answer": "<strong>Choice 'D'</strong> is the correct answer.  ",
  "solution": "",
  "distractor_explanations": {},
  "tags": [
    "VAR-4.E.1",
    "VAR-4.E",
    "3.A",
    "VAR-4"
  ],
  "standards": [
    "VAR-4.E.1",
    "VAR-4.E",
    "3.A",
    "VAR-4"
  ]
}