{
  "question_id": "question-081",
  "title": "Measuring Distribution Spread",
  "difficulty": "Easy",
  "question_text": "<div class=\"paragraph\">All of the following are ways to measure or display the spread of a distribution EXCEPT</div>",
  "image_files": [],
  "choices": [
    {
      "letter": "A",
      "text": "Range."
    },
    {
      "letter": "B",
      "text": "Interquartile range."
    },
    {
      "letter": "C",
      "text": "An outlier."
    },
    {
      "letter": "D",
      "text": "Boxplots."
    },
    {
      "letter": "E",
      "text": "Five-number summaries."
    }
  ],
  "correct_answer": "<strong>Choice 'C'</strong> is the correct answer.  ",
  "solution": "",
  "distractor_explanations": {},
  "tags": [
    "UNC-1.J.2",
    "2.C",
    "UNC-1.J.1",
    "UNC-1.J",
    "UNC-1"
  ],
  "standards": [
    "UNC-1.J.2",
    "2.C",
    "UNC-1.J.1",
    "UNC-1.J",
    "UNC-1"
  ]
}