{
  "question_id": "question-044",
  "unit": "Unit 1 | Exploring One-Variable Data",
  "topics": [
    "categorical-data",
    "bar-charts",
    "exploring-data"
  ],
  "title": "From One Graphical Representation to Another",
  "difficulty": "Hard",
  "question_text": "At The Marvelous Marshmallow Market, customers were invited to suggest a new flavor for marshmallows. The finalists were announced and a vote was held. Results of the vote are displayed in the graph below.<br>Created for Albert.io. Copyright 2016. All rights reserved.<br><br>If $200$ votes were cast, which of the following graphs displays the frequency distribution for the votes?",
  "image_files": [
    "images/question-044-img1.PNG",
    "images/question-044-img2.PNG",
    "images/question-044-img3.PNG",
    "images/question-044-img4.PNG",
    "images/question-044-img5.PNG",
    "images/question-044-img6.PNG"
  ],
  "tables": [],
  "choices": [
    {
      "letter": "A",
      "text": "Created for Albert.io. Copyright 2016. All rights reserved."
    },
    {
      "letter": "B",
      "text": "Created for Albert.io. Copyright 2016. All rights reserved."
    },
    {
      "letter": "C",
      "text": "Created for Albert.io. Copyright 2016. All rights reserved."
    },
    {
      "letter": "D",
      "text": "Created for Albert.io. Copyright 2016. All rights reserved."
    },
    {
      "letter": "E",
      "text": "Created for Albert.io. Copyright 2016. All rights reserved."
    }
  ],
  "correct_answer": "Choice 'D' is the correct answer.",
  "solution": "",
  "explanations": {},
  "tags": [
    "UNC-1.C.3",
    "2.B",
    "UNC-1.C",
    "UNC-1"
  ]
}