{
  "question_id": "question-211",
  "unit": "Unit 1 | Exploring One-Variable Data",
  "topics": [
    "normal-distributions",
    "anticipating-patterns",
    "model-for-measurements",
    "mean"
  ],
  "title": "Golf Drives",
  "difficulty": "Easy",
  "question_text": "A local driving range keeps track of the distances its clients hit golf balls. Distances are normally distributed and have a standard deviation of $43\\text{ yards}$.<br>If a $350\\text{ yard}$ drive puts an individual in the top $1\\%$ of all drives, what is the mean of this distribution?",
  "image_files": [],
  "tables": [],
  "choices": [
    {
      "letter": "A",
      "text": "About $250\\text{ yards}$."
    },
    {
      "letter": "B",
      "text": "About $450\\text{ yards}$."
    },
    {
      "letter": "C",
      "text": "About $350\\text{ yards}$."
    },
    {
      "letter": "D",
      "text": "About $295\\text{ yards}$."
    },
    {
      "letter": "E",
      "text": "About $268\\text{ yards}$."
    }
  ],
  "correct_answer": "Choice 'A' is the correct answer.",
  "solution": "This problem tests students’ ability to use the normal tables and algebra to solve for the mean. Using Table A from your AP Statistics tables, you can find where the $z$-value would be for approximately $0.9900$, which ends up being at $2.3$ and $0.03$ with a $p$-value of $0.9901$.\n\nSet up the following equation and solve for $x$ to get $x = 250$:\n\n$$\\frac{350-x}{43} = 2.33$$\n\n$$350-x=100.19$$\n\n$$-x=-249.81$$\n\n$$x=249.81$$\n\nChoice 'A' is correct.",
  "tags": [
    "VAR-2.B.2",
    "VAR-2.B",
    "VAR-2.B.1",
    "3.A",
    "VAR-2.B.4",
    "VAR-2"
  ]
}